shikibaio/__init__.py
shikibaio/_dispatcher.py
shikibaio/adapt_clients/__init__.py
shikibaio/adapt_clients/base.py
shikibaio/adapt_clients/shiki4py.py
shikibaio/adapt_clients/shikithon.py
shikibaio/enums/__init__.py
shikibaio/enums/data_type.py
shikibaio/enums/event_type.py
shikibaio/handlers.py
shikibaio/py.typed
shikibaio/types/__init__.py
shikibaio/types/event.py
shikibaio-0.1.0b0.dist-info/LICENSE
shikibaio-0.1.0b0.dist-info/WHEEL
shikibaio-0.1.0b0.dist-info/METADATA
shikibaio-0.1.0b0.dist-info/RECORD
