Metadata-Version: 2.1
Name: shikibaio
Version: 0.1.0b0
Summary: Asynchronous bot development framework for shikimori.
Home-page: https://github.com/ren3104/shikibaio
License: MIT
Keywords: shikimori,shikibaio,bot,bot-framework,asyncio
Author: ren3104
Author-email: 2ren3104@gmail.com
Requires-Python: >=3.7,<3.10
Classifier: License :: OSI Approved :: MIT License
Classifier: Programming Language :: Python :: 3
Classifier: Programming Language :: Python :: 3.7
Classifier: Programming Language :: Python :: 3.8
Classifier: Programming Language :: Python :: 3.9
Classifier: Typing :: Typed
Requires-Dist: aiocometd (>=0.4.5,<0.5.0)
Project-URL: Bug Tracker, https://github.com/ren3104/shikibaio/issues
Project-URL: Repository, https://github.com/ren3104/shikibaio
